ConstantVelocityAcquisitionPlugin/__init__.py
ConstantVelocityAcquisitionPlugin/constant_velocity_acquisition.py
ConstantVelocityAcquisitionPlugin/main.py
ConstantVelocityAcquisitionPlugin/controller/__init__.py
ConstantVelocityAcquisitionPlugin/controller/constant_velocity_acquisition_controller.py
ConstantVelocityAcquisitionPlugin/model/__init__.py
ConstantVelocityAcquisitionPlugin/model/features/ConstantVelocityAcquisition_feature.py
ConstantVelocityAcquisitionPlugin/model/features/__init__.py
ConstantVelocityAcquisitionPlugin/view/__init__.py
ConstantVelocityAcquisitionPlugin/view/constant_velocity_acquisition_frame.py
navigate_constant_velocity-0.0.1.dist-info/LICENSE
navigate_constant_velocity-0.0.1.dist-info/METADATA
navigate_constant_velocity-0.0.1.dist-info/WHEEL
navigate_constant_velocity-0.0.1.dist-info/entry_points.txt
navigate_constant_velocity-0.0.1.dist-info/top_level.txt
navigate_constant_velocity-0.0.1.dist-info/RECORD
