Metadata-Version: 2.1
Name: navigate-constant-velocity
Version: 0.0.1
Summary: A navigate plugin for imaging in a constant velocity format.
Author: The Dean Lab, UT Southwestern Medical Center
License: MIT License
Project-URL: Source, https://github.com/TheDeanLab/navigate-constant-velocity-acquisition
Classifier: Intended Audience :: Developers
Classifier: Operating System :: POSIX :: Linux
Classifier: Operating System :: MacOS :: MacOS X
Classifier: Operating System :: Microsoft :: Windows
Classifier: Programming Language :: Python :: 3.9
Classifier: Programming Language :: Python :: Implementation :: CPython
Classifier: Programming Language :: Python :: Implementation :: PyPy
License-File: LICENSE
